timingdiagram/__init__.py
timingdiagram_alkasm-0.4.1.dist-info/LICENSE
timingdiagram_alkasm-0.4.1.dist-info/WHEEL
timingdiagram_alkasm-0.4.1.dist-info/METADATA
timingdiagram_alkasm-0.4.1.dist-info/RECORD
