Metadata-Version: 2.1
Name: timingdiagram-alkasm
Version: 0.4.1
Summary: Temporal boolean algebra.
Home-page: https://github.com/alkasm/timingdiagram
License: UNKNOWN
Author: Alexander Reynolds
Author-email: ar@reynoldsalexander.com
Requires-Python: >=3.6
Classifier: Programming Language :: Python :: 3
Classifier: License :: OSI Approved :: MIT License
Classifier: Operating System :: OS Independent
Requires-Dist: sortedcollections
